{
  "timestamp": "2026-07-16 10:52:26",
  "frame_index": 2702,
  "mango_id": 30,
  "track_id": 30,
  "label": "mango_overripe",
  "confidence": "0.8595",
  "x1": 67,
  "y1": 247,
  "x2": 472,
  "y2": 478,
  "center_x": 269,
  "center_y": 362,
  "area_px": 108984,
  "stable_frames": 39,
  "first_frame": 2664,
  "last_frame": 2702,
  "consistency_score": "1.0000",
  "consistency_label": "高",
  "rgb_r_mean": "132.4389",
  "rgb_g_mean": "98.4380",
  "rgb_b_mean": "72.1680",
  "hsv_h_mean_deg": "70.2121",
  "hsv_s_mean_pct": "49.5790",
  "hsv_v_mean_pct": "52.0006",
  "green_ratio": "0.1267",
  "yellow_orange_ratio": "0.8089",
  "dark_spot_ratio": "0.2583",
  "brown_area_ratio": "0.4883"
}
